georchestra_analytics_cli/__init__.py
georchestra_analytics_cli/__main__.py
georchestra_analytics_cli/utils.py
georchestra_analytics_cli/access_logs/AccessLogProcessor.py
georchestra_analytics_cli/access_logs/__init__.py
georchestra_analytics_cli/access_logs/app_processors/__init__.py
georchestra_analytics_cli/access_logs/app_processors/abstract.py
georchestra_analytics_cli/access_logs/app_processors/generic.py
georchestra_analytics_cli/access_logs/app_processors/geoserver.py
georchestra_analytics_cli/access_logs/log_parsers/AbstractLogParser.py
georchestra_analytics_cli/access_logs/log_parsers/BaseLogParser.py
georchestra_analytics_cli/access_logs/log_parsers/FakeLogGenerator.py
georchestra_analytics_cli/access_logs/log_parsers/OpentelemetryLogParser.py
georchestra_analytics_cli/access_logs/log_parsers/RegexLogParser.py
georchestra_analytics_cli/access_logs/log_parsers/__init__.py
georchestra_analytics_cli/common/__init__.py
georchestra_analytics_cli/common/models.py
georchestra_analytics_cli/config/__init__.py
georchestra_analytics_cli/config/analytics_cli.yaml
georchestra_analytics_cli/config/config.py
georchestra_analytics_cli-0.1.1.dist-info/licenses/LICENSE.txt
georchestra_analytics_cli-0.1.1.dist-info/METADATA
georchestra_analytics_cli-0.1.1.dist-info/WHEEL
georchestra_analytics_cli-0.1.1.dist-info/entry_points.txt
georchestra_analytics_cli-0.1.1.dist-info/top_level.txt
georchestra_analytics_cli-0.1.1.dist-info/RECORD
