Metadata-Version: 2.4
Name: georchestra-analytics-cli
Version: 0.1.1
Summary: A CLI for the geOrchestra analytics module
Home-page: https://github.com/georchestra/analytics
Author: Jean Pommier
Author-email: jean.pommier@pi-geosolutions.fr
License: GPL-3.0-only
Project-URL: Documentation, https://docs.georchestra.org/analytics
Project-URL: Source, https://github.com/georchestra/analytics
Platform: any
Classifier: Development Status :: 4 - Beta
Classifier: Programming Language :: Python
Requires-Python: >=3.10
License-File: LICENSE.txt
Requires-Dist: importlib-metadata; python_version < "3.8"
Requires-Dist: Click
Requires-Dist: prometheus_client<1.0,>=0.21.0
Requires-Dist: pyaml_env<2.0,>=1.2
Requires-Dist: pydantic
Requires-Dist: SQLAlchemy
Requires-Dist: psycopg2-binary
Requires-Dist: python-dateutil
Provides-Extra: dev
Requires-Dist: tox; extra == "dev"
Requires-Dist: black; extra == "dev"
Requires-Dist: isort; extra == "dev"
Provides-Extra: testing
Requires-Dist: setuptools; extra == "testing"
Requires-Dist: pytest; extra == "testing"
Requires-Dist: pytest-cov; extra == "testing"
Dynamic: license-file
